zuul_registry/__init__.py
zuul_registry/filesystem.py
zuul_registry/hasher.py
zuul_registry/main.py
zuul_registry/s3.py
zuul_registry/storage.py
zuul_registry/storageutils.py
zuul_registry/swift.py
zuul_registry-1.3.0.dist-info/COPYING
zuul_registry-1.3.0.dist-info/METADATA
zuul_registry-1.3.0.dist-info/WHEEL
zuul_registry-1.3.0.dist-info/entry_points.txt
zuul_registry-1.3.0.dist-info/pbr.json
zuul_registry-1.3.0.dist-info/top_level.txt
zuul_registry-1.3.0.dist-info/RECORD
