Metadata-Version: 2.1
Name: zuul-registry
Version: 1.3.0
Summary: A speculative container image registry for Zuul
Home-page: https://zuul-ci.org/
Author: Zuul Team
Author-email: zuul-discuss@lists.zuul-ci.org
Classifier: Intended Audience :: Information Technology
Classifier: Intended Audience :: System Administrators
Classifier: License :: OSI Approved :: GNU General Public License v3 (GPLv3)
Classifier: Operating System :: POSIX :: Linux
Classifier: Programming Language :: Python
Classifier: Programming Language :: Python :: 3
Classifier: Programming Language :: Python :: 3.5
Requires-Python: >=3.5
License-File: COPYING
Requires-Dist: PyYAML
Requires-Dist: boto3
Requires-Dist: cherrypy
Requires-Dist: openstacksdk
Requires-Dist: pbr >=1.1.0
Requires-Dist: pyjwt <3.0.0,>=2.0.0
Requires-Dist: python-dateutil
Requires-Dist: requests
Requires-Dist: routes
Requires-Dist: sha256 >=1.0
